LICENSE.txt
MANIFEST.in
README.md
setup.py
getgauge/__init__.py
getgauge/exceptions.py
getgauge/executor.py
getgauge/handlers.py
getgauge/impl_loader.py
getgauge/logger.py
getgauge/parser.py
getgauge/processor.py
getgauge/python.py
getgauge/refactor.py
getgauge/registry.py
getgauge/static_loader.py
getgauge/util.py
getgauge/validator.py
getgauge.egg-info/PKG-INFO
getgauge.egg-info/SOURCES.txt
getgauge.egg-info/dependency_links.txt
getgauge.egg-info/requires.txt
getgauge.egg-info/top_level.txt
getgauge/messages/__init__.py
getgauge/messages/messages_pb2.py
getgauge/messages/services_pb2.py
getgauge/messages/services_pb2_grpc.py
getgauge/messages/spec_pb2.py
tests/test_impl_loader.py
tests/test_parser.py
tests/test_processor.py
tests/test_python.py
tests/test_refactor.py
tests/test_registry.py
tests/test_static_loader.py
tests/test_utils.py
tests/test_validate.py